README.md
setup.py
lade/__init__.py
lade/decoding.py
lade/utils.py
lade.egg-info/PKG-INFO
lade.egg-info/SOURCES.txt
lade.egg-info/dependency_links.txt
lade.egg-info/top_level.txt
lade/models/llama.py